[
    {
        "id": 1,
        "name": "Uprawa nr 1",
        "variety": 1,
        "quantity": 800,
        "humidity": 55,
        "temperature": 27,
        "watering": true
    },
    {
        "id": 2,
        "name": "Uprawa nr 2",
        "variety": 2,
        "quantity": 1200,
        "humidity": 70,
        "temperature": 31,
        "watering": false
    },
    {
        "id": 3,
        "name": "Uprawa nr 3",
        "variety": 3,
        "quantity": 1500,
        "humidity": 65,
        "temperature": 24,
        "watering": false
    },
    {
        "id": 4,
        "name": "Uprawa nr 4",
        "variety": 4,
        "quantity": 1000,
        "humidity": 60,
        "temperature": 25,
        "watering": false
    },
    {
        "id": 5,
        "name": "Uprawa nr 5",
        "variety": 5,
        "quantity": 900,
        "humidity": 50,
        "temperature": 29,
        "watering":  true
    },
    {
        "id": 6,
        "name": "Uprawa nr 6",
        "variety": 6,
        "quantity": 1100,
        "humidity": 75,
        "temperature": 25,
        "watering": false
    },
    {
        "id": 7,
        "name": "Uprawa nr 7",
        "variety": 7,
        "quantity": 950,
        "humidity": 58,
        "temperature": 26,
        "watering": true
    }
]